<?xml version="1.0" encoding="UTF-8"?>
<con:soapui-project id="b692b32f-bddf-431a-8549-f60ec6514398" created="2.2.0" activeEnvironment="DEV" name="Claire Statements" resourceRoot="" updated="2.3.0 2018-03-06T16:28:42Z" encryptionMode="Not encrypted" xmlns:con="http://eviware.com/soapui/config"><con:settings/><con:interface xsi:type="con:RestService" id="ff5cf5b9-b5e3-4a21-8d10-f7ff24cfe0d2" wadlVersion="http://wadl.dev.java.net/2009/02" name="Claire Statements" type="rest" xmlns:xsi="http://www.w3.org/2001/XMLSchema-instance"><con:settings/><con:definitionCache type="TEXT" rootPart=""/><con:endpoints><con:endpoint>http://d3-pl-app01.dev.medfusion.net:8082</con:endpoint></con:endpoints><con:environmentSpec><con:entry environmentId="53ad3771-41b4-4436-975b-f8de65a9c7be"><con:authProfile>Inherit From Parent</con:authProfile></con:entry><con:entry environmentId="f341cae1-7249-4bd8-bac5-6a44d5598587"><con:authProfile>Inherit From Parent</con:authProfile></con:entry><con:entry environmentId="a7c3fc61-ebc7-4257-b499-e5eec407200b"><con:authProfile>Inherit From Parent</con:authProfile></con:entry></con:environmentSpec><con:resource name="" path="/claire-statements/v1/persons/{personId}/statements" id="ee2fd74b-7351-4332-805d-ceda0c40b5a5"><con:settings/><con:parameters><con:parameter><con:name>personId</con:name><con:value>1</con:value><con:style>TEMPLATE</con:style><con:default>1</con:default></con:parameter><con:parameter><con:name>id</con:name><con:value>1</con:value><con:style>TEMPLATE</con:style><con:default>1</con:default></con:parameter><con:parameter><con:name>Authorization</con:name><con:value/><con:style>HEADER</con:style><con:default/><con:description xsi:nil="true"/></con:parameter><con:parameter><con:name>ticketId</con:name><con:value/><con:style>QUERY</con:style><con:default/><con:description xsi:nil="true"/></con:parameter><con:parameter><con:name>portalId</con:name><con:value/><con:style>QUERY</con:style><con:default/><con:description xsi:nil="true"/></con:parameter></con:parameters><con:resource name="" path="{id}" id="e57f08a0-7861-4d28-bc02-a1357137bec3"><con:settings/><con:parameters><con:parameter><con:name>id</con:name><con:value>id</con:value><con:style>TEMPLATE</con:style><con:default>id</con:default></con:parameter></con:parameters><con:method name="Get Statements" id="420ffef3-76a6-4f19-814b-9bdc19f7f422" method="GET"><con:settings/><con:parameters/><con:request name="Get Statement" id="ca93d2f7-5529-4ef1-914e-f3db60d9f65c" mediaType="application/json"><con:settings><con:setting id="com.eviware.soapui.impl.wsdl.WsdlRequest@request-headers">&lt;xml-fragment/></con:setting></con:settings><con:endpoint>http://d3-pl-app01.dev.medfusion.net:8082</con:endpoint><con:request/><con:credentials><con:selectedAuthProfile>No Authorization</con:selectedAuthProfile><con:authType>No Authorization</con:authType></con:credentials><con:jmsConfig JMSDeliveryMode="PERSISTENT"/><con:parameters/><con:environmentSpec><con:entry environmentId="53ad3771-41b4-4436-975b-f8de65a9c7be"><con:authProfile>Inherit From Parent</con:authProfile></con:entry><con:entry environmentId="f341cae1-7249-4bd8-bac5-6a44d5598587"><con:authProfile>Inherit From Parent</con:authProfile></con:entry><con:entry environmentId="a7c3fc61-ebc7-4257-b499-e5eec407200b"><con:authProfile>Inherit From Parent</con:authProfile></con:entry></con:environmentSpec></con:request><con:environmentSpec><con:entry environmentId="53ad3771-41b4-4436-975b-f8de65a9c7be"><con:authProfile>Inherit From Parent</con:authProfile></con:entry><con:entry environmentId="f341cae1-7249-4bd8-bac5-6a44d5598587"><con:authProfile>Inherit From Parent</con:authProfile></con:entry><con:entry environmentId="a7c3fc61-ebc7-4257-b499-e5eec407200b"><con:authProfile>Inherit From Parent</con:authProfile></con:entry></con:environmentSpec></con:method><con:method name="Delete Statements" id="32595c7a-7fc4-47f3-aa59-fd1ecc846fab" method="DELETE"><con:settings/><con:parameters/><con:representation type="REQUEST"><con:mediaType>application/json</con:mediaType><con:params/></con:representation><con:representation type="RESPONSE"><con:mediaType xsi:nil="true"/><con:status>200</con:status><con:params/><con:element>data</con:element></con:representation><con:representation type="FAULT"><con:mediaType>application/json;charset=UTF-8</con:mediaType><con:status>405 404</con:status><con:params/><con:element xmlns:ac6="http://d3-pl-app01.dev.medfusion.net/claire-statements/v1/persons/17739/statements/5ac6726cffdaa5523b628ce3">ac6:Fault</con:element></con:representation><con:representation type="FAULT"><con:mediaType>application/json;charset=ISO-8859-1</con:mediaType><con:status>401</con:status><con:params/><con:element>Fault</con:element></con:representation><con:request name="Delete Statements" id="fd6c167f-cb3c-4bfe-8400-0769314f4553" mediaType="application/json" postQueryString="false"><con:settings><con:setting id="com.eviware.soapui.impl.wsdl.WsdlRequest@request-headers">&lt;xml-fragment/></con:setting></con:settings><con:endpoint>http://d3-pl-app01.dev.medfusion.net:8082</con:endpoint><con:request/><con:credentials><con:selectedAuthProfile>No Authorization</con:selectedAuthProfile><con:authType>No Authorization</con:authType></con:credentials><con:jmsConfig JMSDeliveryMode="PERSISTENT"/><con:parameters/><con:environmentSpec><con:entry environmentId="53ad3771-41b4-4436-975b-f8de65a9c7be"><con:authProfile>Inherit From Parent</con:authProfile></con:entry><con:entry environmentId="f341cae1-7249-4bd8-bac5-6a44d5598587"><con:authProfile>Inherit From Parent</con:authProfile></con:entry><con:entry environmentId="a7c3fc61-ebc7-4257-b499-e5eec407200b"><con:authProfile>Inherit From Parent</con:authProfile></con:entry></con:environmentSpec></con:request><con:environmentSpec><con:entry environmentId="53ad3771-41b4-4436-975b-f8de65a9c7be"><con:authProfile>Inherit From Parent</con:authProfile></con:entry><con:entry environmentId="f341cae1-7249-4bd8-bac5-6a44d5598587"><con:authProfile>Inherit From Parent</con:authProfile></con:entry><con:entry environmentId="a7c3fc61-ebc7-4257-b499-e5eec407200b"><con:authProfile>Inherit From Parent</con:authProfile></con:entry></con:environmentSpec></con:method><con:environmentSpec><con:entry environmentId="53ad3771-41b4-4436-975b-f8de65a9c7be"><con:authProfile>Inherit From Parent</con:authProfile></con:entry><con:entry environmentId="f341cae1-7249-4bd8-bac5-6a44d5598587"><con:authProfile>Inherit From Parent</con:authProfile></con:entry><con:entry environmentId="a7c3fc61-ebc7-4257-b499-e5eec407200b"><con:authProfile>Inherit From Parent</con:authProfile></con:entry></con:environmentSpec></con:resource><con:method name="Add a Statement" id="9998b04d-6f9b-4010-ade8-81dbe6c98627" method="POST"><con:settings/><con:parameters/><con:representation type="REQUEST"><con:mediaType>application/json</con:mediaType><con:params/></con:representation><con:representation type="RESPONSE"><con:mediaType>application/json;charset=UTF-8</con:mediaType><con:status>200</con:status><con:params/><con:element>Response</con:element></con:representation><con:representation type="FAULT"><con:mediaType>application/json;charset=UTF-8</con:mediaType><con:status>403 400</con:status><con:params/><con:element xmlns:stat="http://d3-pl-app01.dev.medfusion.net/claire-statements/v1/persons/17739/statements">stat:Fault</con:element></con:representation><con:representation type="FAULT"><con:mediaType>application/json;charset=ISO-8859-1</con:mediaType><con:status>401</con:status><con:params/><con:element>Fault</con:element></con:representation><con:representation type="RESPONSE"><con:mediaType xsi:nil="true"/><con:status>0</con:status><con:params/><con:element>data</con:element></con:representation><con:request name="Add a Statement" id="ad52b265-ac3d-49a4-a4ef-65097d6b51b8" mediaType="application/json" postQueryString="false"><con:settings><con:setting id="com.eviware.soapui.impl.wsdl.WsdlRequest@request-headers">&lt;xml-fragment/></con:setting></con:settings><con:endpoint>http://d3-pl-app01.dev.medfusion.net:8082</con:endpoint><con:request>[
  {
    "amount": 0,
    "createdDate": "string",
    "dueDate": "string",
    "id": "string",
    "modifiedDate": "string",
    "personId": "string",
    "portalId": "string",
    "statementId": "string",
    "ticketId": "string"
  }
]</con:request><con:credentials><con:selectedAuthProfile>No Authorization</con:selectedAuthProfile><con:authType>No Authorization</con:authType></con:credentials><con:jmsConfig JMSDeliveryMode="PERSISTENT"/><con:parameters/><con:parameterOrder><con:entry>Authorization</con:entry><con:entry>personId</con:entry><con:entry>id</con:entry><con:entry>ticketId</con:entry><con:entry>portalId</con:entry></con:parameterOrder><con:environmentSpec><con:entry environmentId="53ad3771-41b4-4436-975b-f8de65a9c7be"><con:authProfile>Inherit From Parent</con:authProfile></con:entry><con:entry environmentId="f341cae1-7249-4bd8-bac5-6a44d5598587"><con:authProfile>Inherit From Parent</con:authProfile></con:entry><con:entry environmentId="a7c3fc61-ebc7-4257-b499-e5eec407200b"><con:authProfile>Inherit From Parent</con:authProfile></con:entry></con:environmentSpec></con:request><con:request name="Copy of SystemJwtValidationClientV1" id="07b904a4-2483-458b-b36c-5f5b68536ac4" mediaType="application/json" postQueryString="false"><con:settings><con:setting id="com.eviware.soapui.impl.wsdl.WsdlRequest@request-headers">&lt;xml-fragment/></con:setting></con:settings><con:endpoint>https://d1-ping-01.dev.medfusion.net:9031</con:endpoint><con:request/><con:originalUri>https://d1-ping-01.dev.medfusion.net/as/token.oauth2</con:originalUri><con:credentials><con:selectedAuthProfile>No Authorization</con:selectedAuthProfile><con:authType>No Authorization</con:authType></con:credentials><con:jmsConfig JMSDeliveryMode="PERSISTENT"/><con:parameters>
  <con:entry key="grant_type" value="client_credentials"/>
  <con:entry key="client_secret" value="${#Project#client_secret}"/>
  <con:entry key="client_id" value="SystemValidationClientV1"/>
</con:parameters><con:parameterOrder><con:entry>grant_type</con:entry><con:entry>client_id</con:entry><con:entry>client_secret</con:entry></con:parameterOrder></con:request><con:request name="Copy of SystemValidationClientV1" id="9152bd40-ab90-49eb-bb26-e86281d6474e" mediaType="application/json" postQueryString="false"><con:settings/><con:endpoint>https://d1-ping-01.dev.medfusion.net:9031</con:endpoint><con:request/><con:credentials><con:selectedAuthProfile>No Authorization</con:selectedAuthProfile><con:authType>No Authorization</con:authType></con:credentials><con:jmsConfig JMSDeliveryMode="PERSISTENT"/><con:parameters><entry key="client_secret" value="${#Project#client_secret}" xmlns="http://eviware.com/soapui/config"/></con:parameters></con:request><con:environmentSpec><con:entry environmentId="53ad3771-41b4-4436-975b-f8de65a9c7be"><con:authProfile>Inherit From Parent</con:authProfile></con:entry><con:entry environmentId="f341cae1-7249-4bd8-bac5-6a44d5598587"><con:authProfile>Inherit From Parent</con:authProfile></con:entry><con:entry environmentId="a7c3fc61-ebc7-4257-b499-e5eec407200b"><con:authProfile>Inherit From Parent</con:authProfile></con:entry></con:environmentSpec></con:method><con:method name="Get Statements" id="144857ee-1597-427d-b819-a0d66ce80bd0" method="GET"><con:settings/><con:parameters/><con:representation type="RESPONSE"><con:mediaType>application/json;charset=UTF-8</con:mediaType><con:status>200</con:status><con:params/><con:element>Response</con:element></con:representation><con:representation type="FAULT"><con:mediaType>application/json;charset=UTF-8</con:mediaType><con:status>403 404</con:status><con:params/><con:element xmlns:stat="http://d3-pl-app01.dev.medfusion.net/claire-statements/v1/persons/17739/statements">stat:Fault</con:element></con:representation><con:representation type="FAULT"><con:mediaType>application/json;charset=ISO-8859-1</con:mediaType><con:status>401</con:status><con:params/><con:element>Fault</con:element></con:representation><con:request name="Get Statements" id="aaf21177-8233-4b3c-a04e-506b63d89fba" mediaType="application/json"><con:settings><con:setting id="com.eviware.soapui.impl.wsdl.WsdlRequest@request-headers">&lt;xml-fragment/></con:setting></con:settings><con:endpoint>http://d3-pl-app01.dev.medfusion.net:8082</con:endpoint><con:request/><con:credentials><con:selectedAuthProfile>No Authorization</con:selectedAuthProfile><con:authType>No Authorization</con:authType></con:credentials><con:jmsConfig JMSDeliveryMode="PERSISTENT"/><con:parameters/><con:parameterOrder><con:entry>Authorization</con:entry><con:entry>personId</con:entry><con:entry>id</con:entry><con:entry>ticketId</con:entry><con:entry>portalId</con:entry></con:parameterOrder><con:environmentSpec><con:entry environmentId="53ad3771-41b4-4436-975b-f8de65a9c7be"><con:authProfile>Inherit From Parent</con:authProfile></con:entry><con:entry environmentId="f341cae1-7249-4bd8-bac5-6a44d5598587"><con:authProfile>Inherit From Parent</con:authProfile></con:entry><con:entry environmentId="a7c3fc61-ebc7-4257-b499-e5eec407200b"><con:authProfile>Inherit From Parent</con:authProfile></con:entry></con:environmentSpec></con:request><con:environmentSpec><con:entry environmentId="53ad3771-41b4-4436-975b-f8de65a9c7be"><con:authProfile>Inherit From Parent</con:authProfile></con:entry><con:entry environmentId="f341cae1-7249-4bd8-bac5-6a44d5598587"><con:authProfile>Inherit From Parent</con:authProfile></con:entry><con:entry environmentId="a7c3fc61-ebc7-4257-b499-e5eec407200b"><con:authProfile>Inherit From Parent</con:authProfile></con:entry></con:environmentSpec></con:method><con:environmentSpec><con:entry environmentId="53ad3771-41b4-4436-975b-f8de65a9c7be"><con:authProfile>Inherit From Parent</con:authProfile></con:entry><con:entry environmentId="f341cae1-7249-4bd8-bac5-6a44d5598587"><con:authProfile>Inherit From Parent</con:authProfile></con:entry><con:entry environmentId="a7c3fc61-ebc7-4257-b499-e5eec407200b"><con:authProfile>Inherit From Parent</con:authProfile></con:entry></con:environmentSpec></con:resource></con:interface><con:interface xsi:type="con:RestService" id="fd11fc62-8a18-4a8e-a51b-132912319955" wadlVersion="http://wadl.dev.java.net/2009/02" name="SystemJwtValidationClientV1" type="rest" definitionUrl="file:/C:/Users/kgladieux/Desktop/test%20wadl.wadl" basePath="" xmlns:xsi="http://www.w3.org/2001/XMLSchema-instance"><con:settings><con:setting id="com.eviware.soapui.impl.rest.actions.service.Wadl2JavaAction@values-local"><![CDATA[<xml-fragment xmlns:con="http://eviware.com/soapui/config">
  <con:entry key="Automatic Package Names" value="false"/>
  <con:entry key="Output Directory" value=""/>
  <con:entry key="JAXB Customization File(s)" value=""/>
  <con:entry key="Java Args" value=""/>
  <con:entry key="Package" value=""/>
  <con:entry key="Tool Args" value=""/>
</xml-fragment>]]></con:setting></con:settings><con:definitionCache type="TEXT" rootPart="file:/C:/Users/kgladieux/Desktop/test%20wadl.wadl"><con:part><con:url>file:/C:/Users/kgladieux/Desktop/test%20wadl.wadl</con:url><con:content><![CDATA[<application xmlns="http://wadl.dev.java.net/2009/02">
  <doc xml:lang="en" title="SystemJwtValidationClientV1"/>
  <resources base="https://d1-ping-01.dev.medfusion.net:9031">
    <resource path="as/token.oauth2" id="Token.oauth2">
      <doc xml:lang="en" title="Token.oauth2"/>
      <param name="grant_type" default="client_credentials" type="xs:string" required="false" style="query" xmlns:xs="http://www.w3.org/2001/XMLSchema"/>
      <param name="client_id" default="SystemJwtValidationClientV1" type="xs:string" required="false" style="query" xmlns:xs="http://www.w3.org/2001/XMLSchema"/>
      <param name="client_secret" default="lWiNlRcD1snTlSNXmi0GfGFYRHmNtf1iFoawSKAL4M1kICsALm1pF4gwwvEddpIF" type="xs:string" required="false" style="query" xmlns:xs="http://www.w3.org/2001/XMLSchema"/>
      <method name="POST" id="Token.oauth2">
        <doc xml:lang="en" title="Token.oauth2"/>
        <request>
          <param default="client_credentials" name="grant_type" type="xs:string" required="false" style="query" xmlns:xs="http://www.w3.org/2001/XMLSchema"/>
          <param default="SystemValidationClientV1" name="client_id" type="xs:string" required="false" style="query" xmlns:xs="http://www.w3.org/2001/XMLSchema"/>
          <param default="" name="client_secret" type="xs:string" required="false" style="query" xmlns:xs="http://www.w3.org/2001/XMLSchema"/>
          <representation mediaType="application/json"/>
        </request>
        <request>
          <param name="grant_type" default="client_credentials" type="xs:string" required="false" style="query" xmlns:xs="http://www.w3.org/2001/XMLSchema"/>
          <param name="client_id" default="SystemJwtValidationClientV1" type="xs:string" required="false" style="query" xmlns:xs="http://www.w3.org/2001/XMLSchema"/>
          <param default="" name="client_secret" type="xs:string" required="false" style="query" xmlns:xs="http://www.w3.org/2001/XMLSchema"/>
          <representation mediaType="application/json"/>
        </request>
        <response status="200">
          <representation mediaType="application/json; charset=UTF-8"/>
        </response>
        <response status="">
          <representation mediaType="application/json"/>
        </response>
      </method>
    </resource>
  </resources>
</application>]]></con:content><con:type>http://wadl.dev.java.net/2009/02</con:type></con:part></con:definitionCache><con:endpoints><con:endpoint>https://d1-ping-01.dev.medfusion.net:9031</con:endpoint></con:endpoints><con:resource name="Token.oauth2" path="/as/token.oauth2" id="fd7fe056-6491-40cc-adca-7d16861ac9d4"><con:settings/><con:parameters><con:parameter><con:name>grant_type</con:name><con:value>client_credentials</con:value><con:style>QUERY</con:style><con:default>client_credentials</con:default><con:path xsi:nil="true"/><con:description xsi:nil="true"/></con:parameter><con:parameter><con:name>client_id</con:name><con:value>SystemJwtValidationClientV1</con:value><con:style>QUERY</con:style><con:default>SystemJwtValidationClientV1</con:default><con:path xsi:nil="true"/><con:description xsi:nil="true"/></con:parameter><con:parameter><con:name>client_secret</con:name><con:value>lWiNlRcD1snTlSNXmi0GfGFYRHmNtf1iFoawSKAL4M1kICsALm1pF4gwwvEddpIF</con:value><con:style>QUERY</con:style><con:default>lWiNlRcD1snTlSNXmi0GfGFYRHmNtf1iFoawSKAL4M1kICsALm1pF4gwwvEddpIF</con:default><con:path xsi:nil="true"/><con:description xsi:nil="true"/></con:parameter></con:parameters><con:method name="Token.oauth2" id="eafa2aca-690c-4639-a504-57674f503a2b" method="POST"><con:settings/><con:parameters><con:parameter required="false"><con:name>grant_type</con:name><con:value>client_credentials</con:value><con:style>QUERY</con:style><con:type xmlns:xs="http://www.w3.org/2001/XMLSchema">xs:string</con:type><con:default>client_credentials</con:default><con:description xsi:nil="true"/></con:parameter><con:parameter required="false"><con:name>client_id</con:name><con:value>SystemValidationClientV1</con:value><con:style>QUERY</con:style><con:type xmlns:xs="http://www.w3.org/2001/XMLSchema">xs:string</con:type><con:default>SystemValidationClientV1</con:default><con:description xsi:nil="true"/></con:parameter><con:parameter required="false"><con:name>client_secret</con:name><con:value/><con:style>QUERY</con:style><con:type xmlns:xs="http://www.w3.org/2001/XMLSchema">xs:string</con:type><con:default/><con:description xsi:nil="true"/></con:parameter></con:parameters><con:representation type="REQUEST" id=""><con:mediaType>application/json</con:mediaType><con:status/><con:params/><con:description xsi:nil="true"/><con:sampleContent xsi:nil="true"/></con:representation><con:representation type="RESPONSE" id=""><con:mediaType>application/json; charset=UTF-8</con:mediaType><con:status>200</con:status><con:params/><con:description xsi:nil="true"/><con:sampleContent xsi:nil="true"/></con:representation><con:representation type="RESPONSE" id=""><con:mediaType>application/json</con:mediaType><con:status/><con:params/><con:description xsi:nil="true"/><con:sampleContent xsi:nil="true"/></con:representation><con:representation type="FAULT"><con:mediaType>application/json; charset=UTF-8</con:mediaType><con:status>401</con:status><con:params/><con:element xmlns:tok="https://d1-ping-01.dev.medfusion.net/as/token.oauth2">tok:Fault</con:element></con:representation><con:request name="SystemJwtValidationClientV1" id="07b904a4-2483-458b-b36c-5f5b68536ac4" mediaType="application/json" postQueryString="false"><con:settings><con:setting id="com.eviware.soapui.impl.wsdl.WsdlRequest@request-headers">&lt;xml-fragment/></con:setting></con:settings><con:endpoint>https://d1-ping-01.dev.medfusion.net:9031</con:endpoint><con:request/><con:originalUri>https://d1-ping-01.dev.medfusion.net/as/token.oauth2</con:originalUri><con:credentials><con:selectedAuthProfile>No Authorization</con:selectedAuthProfile><con:authType>No Authorization</con:authType></con:credentials><con:jmsConfig JMSDeliveryMode="PERSISTENT"/><con:parameters>
  <con:entry key="grant_type" value="client_credentials"/>
  <con:entry key="client_secret" value="${#Project#client_secret}"/>
  <con:entry key="client_id" value="SystemValidationClientV1"/>
</con:parameters><con:parameterOrder><con:entry>grant_type</con:entry><con:entry>client_id</con:entry><con:entry>client_secret</con:entry></con:parameterOrder></con:request><con:request name="SystemValidationClientV1" id="9152bd40-ab90-49eb-bb26-e86281d6474e" mediaType="application/json" postQueryString="false"><con:settings><con:setting id="com.eviware.soapui.impl.wsdl.WsdlRequest@request-headers">&lt;xml-fragment/></con:setting></con:settings><con:endpoint>https://d1-ping-01.dev.medfusion.net:9031</con:endpoint><con:request/><con:credentials><con:selectedAuthProfile>No Authorization</con:selectedAuthProfile><con:authType>No Authorization</con:authType></con:credentials><con:jmsConfig JMSDeliveryMode="PERSISTENT"/><con:parameters><entry key="client_secret" value="${#Project#client_secret}" xmlns="http://eviware.com/soapui/config"/></con:parameters></con:request></con:method></con:resource></con:interface><con:testSuite id="914a96d4-79e9-4c84-b37b-dc8cd852a7dc" name="Claire-Statements"><con:settings/><con:savedRecentRuns>1</con:savedRecentRuns><con:runType>SEQUENTIAL</con:runType><con:testCase id="0334716d-822d-455c-b68d-c3b8d0811bbe" discardOkResults="true" failOnError="true" failTestCaseOnErrors="true" keepSession="false" name="Add a Statement" searchProperties="true" timeout="0"><con:settings/><con:savedRecentRuns>1</con:savedRecentRuns><con:testStep type="datagen" name="DataGen" id="5bbb399e-c5e9-4eca-a2f6-4250b19c5d2b"><con:settings/><con:config xsi:type="con:DataGeneratorStep" xmlns:xsi="http://www.w3.org/2001/XMLSchema-instance"><con:property type="Script"><con:configuration><script>def sdf = new java.text.SimpleDateFormat("yyyy-MM-dd")
return sdf.format( new Date())</script></con:configuration><con:name>date</con:name><con:mode>READ</con:mode><con:shared>false</con:shared></con:property><con:property type="Number"><con:configuration><start>1</start><end>1000</end><step>1</step><pattern>1</pattern><random>true</random><persist>false</persist></con:configuration><con:name>number</con:name><con:mode>STEP</con:mode><con:shared>false</con:shared></con:property><con:property type="Number"><con:configuration><start>1</start><end>100</end><step/><pattern/><random>true</random><persist>false</persist></con:configuration><con:name>number2</con:name><con:mode>STEP</con:mode><con:shared>false</con:shared></con:property></con:config></con:testStep><con:testStep type="restrequest" name="SystemJwtValidationClientV1" id="87a3013d-6830-4ca3-a5c4-07d4c1aa3e32"><con:settings/><con:config service="SystemJwtValidationClientV1" resourcePath="/as/token.oauth2" methodName="Token.oauth2" xsi:type="con:RestRequestStep" xmlns:xsi="http://www.w3.org/2001/XMLSchema-instance"><con:restRequest name="SystemJwtValidationClientV1" id="4285ed3c-6bc8-4e92-a450-8677817c514d" mediaType="application/json" postQueryString="false"><con:settings><con:setting id="com.eviware.soapui.impl.wsdl.WsdlRequest@request-headers">&lt;xml-fragment/></con:setting></con:settings><con:endpoint>https://d1-ping-01.dev.medfusion.net:9031</con:endpoint><con:request/><con:originalUri>https://d1-ping-01.dev.medfusion.net/as/token.oauth2</con:originalUri><con:assertion type="Valid HTTP Status Codes" id="e617bb1b-a639-420e-9f1e-d0da787cb9d8" name="Valid HTTP Status Codes"><con:settings/><con:configuration><codes>200</codes></con:configuration></con:assertion><con:credentials><con:selectedAuthProfile>No Authorization</con:selectedAuthProfile><con:authType>No Authorization</con:authType></con:credentials><con:jmsConfig JMSDeliveryMode="PERSISTENT"/><con:parameters>
  <con:entry key="grant_type" value="client_credentials"/>
  <con:entry key="client_secret" value="${#Project#client_secret}"/>
  <con:entry key="client_id" value="SystemJwtValidationClientV1"/>
</con:parameters><con:parameterOrder><con:entry>grant_type</con:entry><con:entry>client_id</con:entry><con:entry>client_secret</con:entry></con:parameterOrder></con:restRequest></con:config></con:testStep><con:testStep type="restrequest" name="Add a Statement" id="f8e96dbf-421b-4152-8d5d-367c3dff0d66"><con:settings/><con:config service="Claire Statements" resourcePath="/claire-statements/v1/persons/{personId}/statements" methodName="Add a Statement" xsi:type="con:RestRequestStep" xmlns:xsi="http://www.w3.org/2001/XMLSchema-instance"><con:restRequest name="Add a Statement" id="ad52b265-ac3d-49a4-a4ef-65097d6b51b8" mediaType="application/json" postQueryString="false"><con:settings><con:setting id="com.eviware.soapui.impl.wsdl.WsdlRequest@request-headers">&lt;xml-fragment/></con:setting></con:settings><con:endpoint>http://d3-pl-app01.dev.medfusion.net:8082</con:endpoint><con:request>[
  {
    "amount": ${DataGen#number},
    "statmentId": "kelsey"
  }
]</con:request><con:originalUri>http://d3-pl-app01.dev.medfusion.net/claire-statements/v1/persons/17739/statements</con:originalUri><con:assertion type="Valid HTTP Status Codes" id="63ec8bc0-c529-4b23-8c90-8df80cff4f8b" name="Valid HTTP Status Codes"><con:settings/><con:configuration><codes>200</codes></con:configuration></con:assertion><con:assertion type="JsonPath Existence Match" id="e47b7a64-4311-44b3-ab49-ddf747415f8a" name="Check for existence of [createdDate]"><con:configuration><path>$[0]['createdDate']</path><content>true</content><allowWildcards>false</allowWildcards><ignoreNamspaceDifferences>false</ignoreNamspaceDifferences><ignoreComments>false</ignoreComments></con:configuration></con:assertion><con:credentials><con:selectedAuthProfile>No Authorization</con:selectedAuthProfile><con:authType>No Authorization</con:authType></con:credentials><con:jmsConfig JMSDeliveryMode="PERSISTENT"/><con:parameters>
  <con:entry key="Authorization" value="Bearer ${SystemJwtValidationClientV1#Response#$['access_token']}"/>
  <con:entry key="portalId" value="${#Project#portald}"/>
  <con:entry key="personId" value="${#Project#personId}"/>
  <con:entry key="id" value=""/>
  <con:entry key="ticketId" value="${#Project#ticketId}"/>
</con:parameters><con:parameterOrder><con:entry>Authorization</con:entry><con:entry>personId</con:entry><con:entry>id</con:entry><con:entry>ticketId</con:entry><con:entry>portalId</con:entry></con:parameterOrder><con:environmentSpec><con:entry environmentId="53ad3771-41b4-4436-975b-f8de65a9c7be"><con:authProfile>No Authorization</con:authProfile></con:entry><con:entry environmentId="f341cae1-7249-4bd8-bac5-6a44d5598587"><con:authProfile>No Authorization</con:authProfile></con:entry><con:entry environmentId="a7c3fc61-ebc7-4257-b499-e5eec407200b"><con:authProfile>PROD- SystemJwtValidationClientV1</con:authProfile></con:entry></con:environmentSpec></con:restRequest></con:config></con:testStep><con:testStep type="restrequest" name="Get Statements" id="050cd809-6de4-42b6-9f8f-d0f1ed8678fd"><con:settings/><con:config service="Claire Statements" resourcePath="/claire-statements/v1/persons/{personId}/statements" methodName="Get Statements" xsi:type="con:RestRequestStep" xmlns:xsi="http://www.w3.org/2001/XMLSchema-instance"><con:restRequest name="Get Statements" id="aaf21177-8233-4b3c-a04e-506b63d89fba" mediaType="application/json"><con:settings><con:setting id="com.eviware.soapui.impl.wsdl.WsdlRequest@request-headers">&lt;xml-fragment/></con:setting></con:settings><con:endpoint>http://d3-pl-app01.dev.medfusion.net:8082</con:endpoint><con:request/><con:originalUri>http://d3-pl-app01.dev.medfusion.net/claire-statements/v1/persons/17739/statements</con:originalUri><con:assertion type="Valid HTTP Status Codes" id="62de60a2-f1eb-48a2-bfd2-0a2eb5fa3d01" name="Valid HTTP Status Codes"><con:settings/><con:configuration><codes>200</codes></con:configuration></con:assertion><con:assertion type="JsonPath Existence Match" id="ffe02fa5-c4b3-42ff-9931-07dd31e9b51d" name="Check for existence of [id]"><con:configuration><path>$[0]['id']</path><content>true</content><allowWildcards>false</allowWildcards><ignoreNamspaceDifferences>false</ignoreNamspaceDifferences><ignoreComments>false</ignoreComments></con:configuration></con:assertion><con:credentials><con:selectedAuthProfile>No Authorization</con:selectedAuthProfile><con:authType>No Authorization</con:authType></con:credentials><con:jmsConfig JMSDeliveryMode="PERSISTENT"/><con:parameters>
  <con:entry key="Authorization" value="Bearer ${SystemJwtValidationClientV1#Response#$['access_token']}"/>
  <con:entry key="personId" value="${#Project#personId}"/>
  <con:entry key="id" value=""/>
</con:parameters><con:parameterOrder><con:entry>Authorization</con:entry><con:entry>personId</con:entry><con:entry>id</con:entry><con:entry>ticketId</con:entry><con:entry>portalId</con:entry></con:parameterOrder><con:environmentSpec><con:entry environmentId="53ad3771-41b4-4436-975b-f8de65a9c7be"><con:authProfile>No Authorization</con:authProfile></con:entry><con:entry environmentId="f341cae1-7249-4bd8-bac5-6a44d5598587"><con:authProfile>No Authorization</con:authProfile></con:entry><con:entry environmentId="a7c3fc61-ebc7-4257-b499-e5eec407200b"><con:authProfile>No Authorization</con:authProfile></con:entry></con:environmentSpec></con:restRequest></con:config></con:testStep><con:testStep type="restrequest" name="Get Statement by id" id="82351e4f-0656-4364-ad3b-94699ac6b3ae"><con:settings/><con:config service="Claire Statements" resourcePath="/claire-statements/v1/persons/{personId}/statements" methodName="Get Statements" xsi:type="con:RestRequestStep" xmlns:xsi="http://www.w3.org/2001/XMLSchema-instance"><con:restRequest name="Get Statement by id" id="aaf21177-8233-4b3c-a04e-506b63d89fba" mediaType="application/json"><con:settings><con:setting id="com.eviware.soapui.impl.wsdl.WsdlRequest@request-headers">&lt;xml-fragment/></con:setting></con:settings><con:endpoint>http://d3-pl-app01.dev.medfusion.net:8082</con:endpoint><con:request/><con:originalUri>http://d3-pl-app01.dev.medfusion.net/claire-statements/v1/persons/17739/statements</con:originalUri><con:assertion type="Valid HTTP Status Codes" id="62de60a2-f1eb-48a2-bfd2-0a2eb5fa3d01" name="Valid HTTP Status Codes"><con:settings/><con:configuration><codes>200</codes></con:configuration></con:assertion><con:assertion type="JsonPath Existence Match" id="3219c68c-8c02-4380-a34d-a9245fd3dcdd" name="Check for existence of [id]"><con:configuration><path>$[0]['id']</path><content>true</content><allowWildcards>false</allowWildcards><ignoreNamspaceDifferences>false</ignoreNamspaceDifferences><ignoreComments>false</ignoreComments></con:configuration></con:assertion><con:credentials><con:selectedAuthProfile>No Authorization</con:selectedAuthProfile><con:authType>No Authorization</con:authType></con:credentials><con:jmsConfig JMSDeliveryMode="PERSISTENT"/><con:parameters>
  <con:entry key="Authorization" value="Bearer ${SystemJwtValidationClientV1#Response#$['access_token']}"/>
  <con:entry key="personId" value="${#Project#personId}"/>
  <con:entry key="id" value="${Get Statements#Response#$[0]['id']}"/>
</con:parameters><con:parameterOrder><con:entry>Authorization</con:entry><con:entry>personId</con:entry><con:entry>id</con:entry><con:entry>ticketId</con:entry><con:entry>portalId</con:entry></con:parameterOrder><con:environmentSpec><con:entry environmentId="53ad3771-41b4-4436-975b-f8de65a9c7be"><con:authProfile>No Authorization</con:authProfile></con:entry><con:entry environmentId="f341cae1-7249-4bd8-bac5-6a44d5598587"><con:authProfile>No Authorization</con:authProfile></con:entry><con:entry environmentId="a7c3fc61-ebc7-4257-b499-e5eec407200b"><con:authProfile>Inherit From Parent</con:authProfile></con:entry></con:environmentSpec></con:restRequest></con:config></con:testStep><con:testStep type="restrequest" name="Delete Statements" id="d32ab890-d483-40e3-ac53-7d613194a02d"><con:settings/><con:config service="Claire Statements" resourcePath="/claire-statements/v1/persons/{personId}/statements/{id}" methodName="Delete Statements" xsi:type="con:RestRequestStep" xmlns:xsi="http://www.w3.org/2001/XMLSchema-instance"><con:restRequest name="Delete Statements" id="fd6c167f-cb3c-4bfe-8400-0769314f4553" mediaType="application/json" postQueryString="false"><con:settings><con:setting id="com.eviware.soapui.impl.wsdl.WsdlRequest@request-headers">&lt;xml-fragment/></con:setting></con:settings><con:endpoint>http://d3-pl-app01.dev.medfusion.net:8082</con:endpoint><con:request/><con:originalUri>http://d3-pl-app01.dev.medfusion.net/claire-statements/v1/persons/17739/statements/5ac6726cffdaa5523b628ce3</con:originalUri><con:assertion type="Valid HTTP Status Codes" id="59597606-a296-48d2-875a-1cca03277a0d" name="Valid HTTP Status Codes"><con:settings/><con:configuration><codes>200</codes></con:configuration></con:assertion><con:credentials><con:selectedAuthProfile>No Authorization</con:selectedAuthProfile><con:authType>No Authorization</con:authType></con:credentials><con:jmsConfig JMSDeliveryMode="PERSISTENT"/><con:parameters>
  <con:entry key="Authorization" value="Bearer ${SystemJwtValidationClientV1#Response#$['access_token']}"/>
  <con:entry key="personId" value="${#Project#personId}"/>
  <con:entry key="id" value="${Get Statements#Response#$[0]['id']}"/>
</con:parameters><con:parameterOrder><con:entry>Authorization</con:entry><con:entry>personId</con:entry><con:entry>id</con:entry><con:entry>ticketId</con:entry><con:entry>portalId</con:entry></con:parameterOrder><con:environmentSpec><con:entry environmentId="53ad3771-41b4-4436-975b-f8de65a9c7be"><con:authProfile>No Authorization</con:authProfile></con:entry><con:entry environmentId="f341cae1-7249-4bd8-bac5-6a44d5598587"><con:authProfile>No Authorization</con:authProfile></con:entry><con:entry environmentId="a7c3fc61-ebc7-4257-b499-e5eec407200b"><con:authProfile>Inherit From Parent</con:authProfile></con:entry></con:environmentSpec></con:restRequest></con:config></con:testStep><con:properties/><con:reportParameters/><con:breakPoints><con:testStepId>5bbb399e-c5e9-4eca-a2f6-4250b19c5d2b</con:testStepId><con:status>NONE</con:status><con:properties/></con:breakPoints><con:breakPoints><con:testStepId>87a3013d-6830-4ca3-a5c4-07d4c1aa3e32</con:testStepId><con:status>NONE</con:status><con:properties/></con:breakPoints><con:environmentSpec><con:entry environmentId="53ad3771-41b4-4436-975b-f8de65a9c7be"><con:authProfile>Inherit From Parent</con:authProfile></con:entry><con:entry environmentId="f341cae1-7249-4bd8-bac5-6a44d5598587"><con:authProfile>Inherit From Parent</con:authProfile></con:entry><con:entry environmentId="a7c3fc61-ebc7-4257-b499-e5eec407200b"><con:authProfile>Inherit From Parent</con:authProfile></con:entry></con:environmentSpec></con:testCase><con:properties/><con:reportParameters/><con:environmentSpec><con:entry environmentId="53ad3771-41b4-4436-975b-f8de65a9c7be"><con:authProfile>Inherit From Parent</con:authProfile></con:entry><con:entry environmentId="f341cae1-7249-4bd8-bac5-6a44d5598587"><con:authProfile>Inherit From Parent</con:authProfile></con:entry><con:entry environmentId="a7c3fc61-ebc7-4257-b499-e5eec407200b"><con:authProfile>Inherit From Parent</con:authProfile></con:entry></con:environmentSpec></con:testSuite><con:savedRecentRuns>1</con:savedRecentRuns><con:requirements/><con:properties><con:property><con:name>username</con:name><con:value>kgladtest+soapui@gmail.com</con:value></con:property><con:property><con:name>password</con:name><con:value>password1</con:value></con:property><con:property><con:name>personId</con:name><con:value/></con:property><con:property><con:name>ticketId</con:name><con:value/></con:property><con:property><con:name>portald</con:name><con:value/></con:property><con:property><con:name>demographicProfileId</con:name></con:property><con:property><con:name>connectionId</con:name></con:property><con:property><con:name>client_secret</con:name></con:property></con:properties><con:wssContainer/><con:databaseConnectionContainer/><con:jmsConnectionContainer/><con:oAuth2ProfileContainer><con:oAuth2Profile><con:name>DEV- SystemJwtValidationClientV1</con:name><con:type>OAuth 2.0</con:type><con:accessTokenURI>https://d1-ping-01.dev.medfusion.net:9031/as/token.oauth2</con:accessTokenURI><con:accessToken>eyJhbGciOiJIUzI1NiIsImtpZCI6InN5c3RlbUp3dCJ9.eyJjbGllbnRfaWQiOiJTeXN0ZW1Kd3RWYWxpZGF0aW9uQ2xpZW50VjEiLCJleHAiOjE1MjM5ODQ3NzQsInNjb3BlIjpbXX0.b6GSNFHtYvUr__QAdDKdEP0WoqSN5HbG2RxOYjVPdSs</con:accessToken><con:accessTokenPosition>HEADER</con:accessTokenPosition><con:accessTokenStartingStatus>EXPIRED</con:accessTokenStartingStatus><con:accessTokenIssuedTime>1523977574</con:accessTokenIssuedTime><con:clientID>SystemJwtValidationClientV1</con:clientID><con:clientSecret>lWiNlRcD1snTlSNXmi0GfGFYRHmNtf1iFoawSKAL4M1kICsALm1pF4gwwvEddpIF</con:clientSecret><con:oAuth2Flow>CLIENT_CREDENTIALS_GRANT</con:oAuth2Flow><con:refreshAccessTokenMethod>AUTOMATIC</con:refreshAccessTokenMethod><con:accessTokenExpirationTime>7199</con:accessTokenExpirationTime><con:responseType>id_token</con:responseType></con:oAuth2Profile><con:oAuth2Profile><con:name>DEMO- SystemJwtValidationClientV1</con:name><con:type>OAuth 2.0</con:type><con:accessTokenURI>https://vip-ping.demo.medfusion.net/as/token.oauth2</con:accessTokenURI><con:accessToken>eyJhbGciOiJIUzI1NiIsImtpZCI6InN5c3RlbUp3dCJ9.eyJjbGllbnRfaWQiOiJTeXN0ZW1Kd3RWYWxpZGF0aW9uQ2xpZW50VjEiLCJleHAiOjE1MjM5ODYyODgsInNjb3BlIjpbXX0.XNbxVwerqR6UOrIgTr-SI-u5egilak9t9vn4Jce_3Fg</con:accessToken><con:accessTokenPosition>HEADER</con:accessTokenPosition><con:accessTokenStartingStatus>RETRIEVED_FROM_SERVER</con:accessTokenStartingStatus><con:accessTokenIssuedTime>1523979088</con:accessTokenIssuedTime><con:clientID>SystemJwtValidationClientV1</con:clientID><con:clientSecret>jEe2y4nuHT9EtAOMW4oZUY9zAmde4SgXIdmRf1gWBlKmFrk98dVxhKAHzGBspPME</con:clientSecret><con:oAuth2Flow>CLIENT_CREDENTIALS_GRANT</con:oAuth2Flow><con:refreshAccessTokenMethod>AUTOMATIC</con:refreshAccessTokenMethod><con:accessTokenExpirationTime>7199</con:accessTokenExpirationTime><con:responseType>id_token</con:responseType></con:oAuth2Profile><con:oAuth2Profile><con:name>PROD- SystemJwtValidationClientV1</con:name><con:type>OAuth 2.0</con:type><con:accessTokenURI>https://vip-ping.medfusion.net/as/token.oauth2</con:accessTokenURI><con:accessToken>eyJhbGciOiJIUzUxMiIsImtpZCI6IjEifQ.eyJjbGllbnRfaWQiOiJTeXN0ZW1Kd3RWYWxpZGF0aW9uQ2xpZW50VjEiLCJleHAiOjE1MjI5NjExNTUsInNjb3BlIjpbXX0.yv6Y72UY1XWJKlifsBf__OFKgy16IrBUu0rBvh6BpPCZER0o96XsN6sqR-lQXJnQKC4PFj3reHPuNLf5aNewhQ</con:accessToken><con:accessTokenPosition>HEADER</con:accessTokenPosition><con:accessTokenStartingStatus>EXPIRED</con:accessTokenStartingStatus><con:accessTokenIssuedTime>1522953955</con:accessTokenIssuedTime><con:clientID>SystemJwtValidationClientV1</con:clientID><con:clientSecret>QBJunWZuyOwEjut17XCLvcLTkPB8HCOtwHc6zcFrmz4X62WHeidhPmCstFPWfHZ6</con:clientSecret><con:oAuth2Flow>CLIENT_CREDENTIALS_GRANT</con:oAuth2Flow><con:refreshAccessTokenMethod>AUTOMATIC</con:refreshAccessTokenMethod><con:accessTokenExpirationTime>7199</con:accessTokenExpirationTime><con:responseType>id_token</con:responseType></con:oAuth2Profile></con:oAuth2ProfileContainer><con:oAuth1ProfileContainer/><con:reporting><con:xmlTemplates/><con:parameters/></con:reporting><con:environment id="53ad3771-41b4-4436-975b-f8de65a9c7be" name="DEV"><con:service type="REST" name="Claire Statements"><con:endpoint authProfile="No Authorization" proxyHost="" proxyPort="" proxyUsername="" proxyPassword="">http://d3-pl-app01.dev.medfusion.net:8082</con:endpoint></con:service><con:service type="REST" name="SystemJwtValidationClientV1"><con:endpoint authProfile="No Authorization" username="" password="" domain="" incomingWss="" outgoingWss="" wssTimeToLive="" wssType="">https://d1-ping-01.dev.medfusion.net:9031</con:endpoint></con:service><con:property><con:name>username</con:name><con:value>kgladtest+soapui@gmail.com</con:value></con:property><con:property><con:name>password</con:name><con:value>password1</con:value></con:property><con:property><con:name>personId</con:name><con:value>17739</con:value></con:property><con:property><con:name>ticketId</con:name><con:value>577008</con:value></con:property><con:property><con:name>portald</con:name><con:value>145</con:value></con:property><con:property><con:name>demographicProfileId</con:name><con:value/></con:property><con:property><con:name>connectionId</con:name><con:value/></con:property><con:property><con:name>client_secret</con:name><con:value>lWiNlRcD1snTlSNXmi0GfGFYRHmNtf1iFoawSKAL4M1kICsALm1pF4gwwvEddpIF</con:value></con:property><con:databaseConnectionContainer/><con:jmsConnectionContainer/></con:environment><con:environment id="f341cae1-7249-4bd8-bac5-6a44d5598587" name="DEMO"><con:service type="REST" name="Claire Statements"><con:endpoint authProfile="No Authorization" proxyHost="" proxyPort="" proxyUsername="" proxyPassword="">http://dm-pl-app11.demo.medfusion.net:8082</con:endpoint></con:service><con:service type="REST" name="SystemJwtValidationClientV1"><con:endpoint authProfile="No Authorization" username="" password="" domain="" incomingWss="" outgoingWss="" wssTimeToLive="" wssType="" proxyHost="" proxyPort="" proxyUsername="" proxyPassword="">https://vip-ping.demo.medfusion.net</con:endpoint></con:service><con:property><con:name>username</con:name><con:value>kgladtest+soapui@gmail.com</con:value></con:property><con:property><con:name>password</con:name><con:value>password1</con:value></con:property><con:property><con:name>personId</con:name><con:value>1352</con:value></con:property><con:property><con:name>ticketId</con:name><con:value>10777</con:value></con:property><con:property><con:name>portald</con:name><con:value>22</con:value></con:property><con:property><con:name>demographicProfileId</con:name><con:value/></con:property><con:property><con:name>connectionId</con:name><con:value/></con:property><con:property><con:name>client_secret</con:name><con:value>jEe2y4nuHT9EtAOMW4oZUY9zAmde4SgXIdmRf1gWBlKmFrk98dVxhKAHzGBspPME</con:value></con:property><con:databaseConnectionContainer/><con:jmsConnectionContainer/></con:environment><con:environment id="a7c3fc61-ebc7-4257-b499-e5eec407200b" name="PROD"><con:service type="REST" name="Claire Statements"><con:endpoint authProfile="No Authorization" proxyHost="" proxyPort="" proxyUsername="" proxyPassword="">http://pr-pl-app01.pub.medfusion.net:8082</con:endpoint></con:service><con:service type="REST" name="SystemJwtValidationClientV1"><con:endpoint authProfile="No Authorization" username="" password="" domain="" incomingWss="" outgoingWss="" wssTimeToLive="" wssType="" proxyHost="" proxyPort="" proxyUsername="" proxyPassword="">https://vip-ping.medfusion.net</con:endpoint></con:service><con:property><con:name>username</con:name><con:value>kgladtest+soapui@gmail.com</con:value></con:property><con:property><con:name>password</con:name><con:value>password1</con:value></con:property><con:property><con:name>personId</con:name><con:value/></con:property><con:property><con:name>ticketId</con:name><con:value/></con:property><con:property><con:name>portald</con:name><con:value>40</con:value></con:property><con:property><con:name>demographicProfileId</con:name><con:value>214563</con:value></con:property><con:property><con:name>connectionId</con:name><con:value>224981</con:value></con:property><con:property><con:name>client_secret</con:name><con:value>QBJunWZuyOwEjut17XCLvcLTkPB8HCOtwHc6zcFrmz4X62WHeidhPmCstFPWfHZ6</con:value></con:property><con:databaseConnectionContainer/><con:jmsConnectionContainer/></con:environment><con:authRepository><con:oAuth20AuthEntry><con:name>DEV- SystemJwtValidationClientV1</con:name><con:type>OAuth 2.0</con:type><con:accessTokenURI>https://d1-ping-01.dev.medfusion.net:9031/as/token.oauth2</con:accessTokenURI><con:accessToken>eyJhbGciOiJIUzI1NiIsImtpZCI6InN5c3RlbUp3dCJ9.eyJjbGllbnRfaWQiOiJTeXN0ZW1Kd3RWYWxpZGF0aW9uQ2xpZW50VjEiLCJleHAiOjE1MjM5ODQ3NzQsInNjb3BlIjpbXX0.b6GSNFHtYvUr__QAdDKdEP0WoqSN5HbG2RxOYjVPdSs</con:accessToken><con:accessTokenPosition>HEADER</con:accessTokenPosition><con:accessTokenStartingStatus>EXPIRED</con:accessTokenStartingStatus><con:accessTokenIssuedTime>1523977574</con:accessTokenIssuedTime><con:clientID>SystemJwtValidationClientV1</con:clientID><con:clientSecret>lWiNlRcD1snTlSNXmi0GfGFYRHmNtf1iFoawSKAL4M1kICsALm1pF4gwwvEddpIF</con:clientSecret><con:oAuth2Flow>CLIENT_CREDENTIALS_GRANT</con:oAuth2Flow><con:refreshAccessTokenMethod>AUTOMATIC</con:refreshAccessTokenMethod><con:accessTokenExpirationTime>7199</con:accessTokenExpirationTime><con:responseType>id_token</con:responseType></con:oAuth20AuthEntry><con:oAuth20AuthEntry><con:name>DEMO- SystemJwtValidationClientV1</con:name><con:type>OAuth 2.0</con:type><con:accessTokenURI>https://vip-ping.demo.medfusion.net/as/token.oauth2</con:accessTokenURI><con:accessToken>eyJhbGciOiJIUzI1NiIsImtpZCI6InN5c3RlbUp3dCJ9.eyJjbGllbnRfaWQiOiJTeXN0ZW1Kd3RWYWxpZGF0aW9uQ2xpZW50VjEiLCJleHAiOjE1MjM5ODYyODgsInNjb3BlIjpbXX0.XNbxVwerqR6UOrIgTr-SI-u5egilak9t9vn4Jce_3Fg</con:accessToken><con:accessTokenPosition>HEADER</con:accessTokenPosition><con:accessTokenStartingStatus>RETRIEVED_FROM_SERVER</con:accessTokenStartingStatus><con:accessTokenIssuedTime>1523979088</con:accessTokenIssuedTime><con:clientID>SystemJwtValidationClientV1</con:clientID><con:clientSecret>jEe2y4nuHT9EtAOMW4oZUY9zAmde4SgXIdmRf1gWBlKmFrk98dVxhKAHzGBspPME</con:clientSecret><con:oAuth2Flow>CLIENT_CREDENTIALS_GRANT</con:oAuth2Flow><con:refreshAccessTokenMethod>AUTOMATIC</con:refreshAccessTokenMethod><con:accessTokenExpirationTime>7199</con:accessTokenExpirationTime><con:responseType>id_token</con:responseType></con:oAuth20AuthEntry><con:oAuth20AuthEntry><con:name>PROD- SystemJwtValidationClientV1</con:name><con:type>OAuth 2.0</con:type><con:accessTokenURI>https://vip-ping.medfusion.net/as/token.oauth2</con:accessTokenURI><con:accessToken>eyJhbGciOiJIUzUxMiIsImtpZCI6IjEifQ.eyJjbGllbnRfaWQiOiJTeXN0ZW1Kd3RWYWxpZGF0aW9uQ2xpZW50VjEiLCJleHAiOjE1MjI5NjExNTUsInNjb3BlIjpbXX0.yv6Y72UY1XWJKlifsBf__OFKgy16IrBUu0rBvh6BpPCZER0o96XsN6sqR-lQXJnQKC4PFj3reHPuNLf5aNewhQ</con:accessToken><con:accessTokenPosition>HEADER</con:accessTokenPosition><con:accessTokenStartingStatus>EXPIRED</con:accessTokenStartingStatus><con:accessTokenIssuedTime>1522953955</con:accessTokenIssuedTime><con:clientID>SystemJwtValidationClientV1</con:clientID><con:clientSecret>QBJunWZuyOwEjut17XCLvcLTkPB8HCOtwHc6zcFrmz4X62WHeidhPmCstFPWfHZ6</con:clientSecret><con:oAuth2Flow>CLIENT_CREDENTIALS_GRANT</con:oAuth2Flow><con:refreshAccessTokenMethod>AUTOMATIC</con:refreshAccessTokenMethod><con:accessTokenExpirationTime>7199</con:accessTokenExpirationTime><con:responseType>id_token</con:responseType></con:oAuth20AuthEntry></con:authRepository><con:environmentSpec><con:entry environmentId="53ad3771-41b4-4436-975b-f8de65a9c7be"><con:authProfile>No Authorization</con:authProfile></con:entry><con:entry environmentId="f341cae1-7249-4bd8-bac5-6a44d5598587"><con:authProfile>No Authorization</con:authProfile></con:entry><con:entry environmentId="a7c3fc61-ebc7-4257-b499-e5eec407200b"><con:authProfile>No Authorization</con:authProfile></con:entry></con:environmentSpec><con:tags/></con:soapui-project>